[{"id":98164,"answer":"Fidel Castro","question":"Trinchera was an organization formed at the University of Havana in 1959 in opposition to this new leader","value":200,"airdate":"2010-02-11T12:00:00.000Z","created_at":"2014-02-14T02:04:04.081Z","updated_at":"2014-02-14T02:04:04.081Z","category_id":13117,"game_id":null,"invalid_count":null,"category":{"id":13117,"title":"power to the students!","created_at":"2014-02-14T02:04:03.991Z","updated_at":"2014-02-14T02:04:03.991Z","clues_count":5}},{"id":98165,"answer":"Dakota Fanning","question":"She sunk her teeth into the role of Jane in 2009's \"New Moon\"","value":200,"airdate":"2010-02-11T12:00:00.000Z","created_at":"2014-02-14T02:04:04.118Z","updated_at":"2014-02-14T02:04:04.118Z","category_id":749,"game_id":null,"invalid_count":null,"category":{"id":749,"title":"actors \u0026 actresses","created_at":"2014-02-11T22:50:06.107Z","updated_at":"2014-02-11T22:50:06.107Z","clues_count":60}},{"id":98166,"answer":"a will","question":"Ideally, witness to this document shouldn't be named in its bequests","value":200,"airdate":"2010-02-11T12:00:00.000Z","created_at":"2014-02-14T02:04:04.157Z","updated_at":"2014-02-14T02:04:04.157Z","category_id":13118,"game_id":null,"invalid_count":null,"category":{"id":13118,"title":"can i get a witness?","created_at":"2014-02-14T02:04:04.011Z","updated_at":"2014-02-14T02:04:04.011Z","clues_count":5}},{"id":98167,"answer":"Afghanistan","question":"Kabul Weekly","value":200,"airdate":"2010-02-11T12:00:00.000Z","created_at":"2014-02-14T02:04:04.194Z","updated_at":"2014-02-14T02:04:04.194Z","category_id":7098,"game_id":null,"invalid_count":null,"category":{"id":7098,"title":"countries by newspaper","created_at":"2014-02-11T23:20:29.738Z","updated_at":"2014-02-11T23:20:29.738Z","clues_count":10}},{"id":98168,"answer":"a bike path (or a bike lane)","question":"In 2009 New York City leaders gathered to paint the last bit of 200 new miles of these for cyclists","value":200,"airdate":"2010-02-11T12:00:00.000Z","created_at":"2014-02-14T02:04:04.233Z","updated_at":"2014-02-14T02:04:04.233Z","category_id":13119,"game_id":null,"invalid_count":null,"category":{"id":13119,"title":"cycle of life","created_at":"2014-02-14T02:04:04.028Z","updated_at":"2014-02-14T02:04:04.028Z","clues_count":5}},{"id":98169,"answer":"smear","question":"A slanderous or defamatory remark, or to spread with a dirty substance","value":200,"airdate":"2010-02-11T12:00:00.000Z","created_at":"2014-02-14T02:04:04.276Z","updated_at":"2014-02-14T02:04:04.276Z","category_id":13120,"game_id":null,"invalid_count":null,"category":{"id":13120,"title":"dirty words","created_at":"2014-02-14T02:04:04.042Z","updated_at":"2014-02-14T02:04:04.042Z","clues_count":5}},{"id":98170,"answer":"disarmament","question":"In Great Britain the youth movement known as the CND is the \"Campaign for Nuclear\" this","value":400,"airdate":"2010-02-11T12:00:00.000Z","created_at":"2014-02-14T02:04:04.327Z","updated_at":"2014-02-14T02:04:04.327Z","category_id":13117,"game_id":null,"invalid_count":null,"category":{"id":13117,"title":"power to the students!","created_at":"2014-02-14T02:04:03.991Z","updated_at":"2014-02-14T02:04:03.991Z","clues_count":5}},{"id":98171,"answer":"Bradley Cooper","question":"This \"The Hangover\" actor has been linked romantically with Renee Zellweger","value":400,"airdate":"2010-02-11T12:00:00.000Z","created_at":"2014-02-14T02:04:04.367Z","updated_at":"2014-02-14T02:04:04.367Z","category_id":749,"game_id":null,"invalid_count":null,"category":{"id":749,"title":"actors \u0026 actresses","created_at":"2014-02-11T22:50:06.107Z","updated_at":"2014-02-11T22:50:06.107Z","clues_count":60}},{"id":98172,"answer":"the grand jury","question":"A target witness is one the government calls before this jury \u0026 really wants to indict","value":400,"airdate":"2010-02-11T12:00:00.000Z","created_at":"2014-02-14T02:04:04.408Z","updated_at":"2014-02-14T02:04:04.408Z","category_id":13118,"game_id":null,"invalid_count":null,"category":{"id":13118,"title":"can i get a witness?","created_at":"2014-02-14T02:04:04.011Z","updated_at":"2014-02-14T02:04:04.011Z","clues_count":5}},{"id":98173,"answer":"the Bahamas","question":"Nassau Guardian","value":400,"airdate":"2010-02-11T12:00:00.000Z","created_at":"2014-02-14T02:04:04.489Z","updated_at":"2014-02-14T02:04:04.489Z","category_id":7098,"game_id":null,"invalid_count":null,"category":{"id":7098,"title":"countries by newspaper","created_at":"2014-02-11T23:20:29.738Z","updated_at":"2014-02-11T23:20:29.738Z","clues_count":10}},{"id":98174,"answer":"a mountain bike","question":"Unlike a hybrid car, a hybrid bicycle uses no electricity; it combines features of a road bike \u0026 this type","value":400,"airdate":"2010-02-11T12:00:00.000Z","created_at":"2014-02-14T02:04:04.527Z","updated_at":"2014-02-14T02:04:04.527Z","category_id":13119,"game_id":null,"invalid_count":null,"category":{"id":13119,"title":"cycle of life","created_at":"2014-02-14T02:04:04.028Z","updated_at":"2014-02-14T02:04:04.028Z","clues_count":5}},{"id":98175,"answer":"soot","question":"From Old Dutch, it's the term for the fine black particles in your chimney","value":400,"airdate":"2010-02-11T12:00:00.000Z","created_at":"2014-02-14T02:04:04.564Z","updated_at":"2014-02-14T02:04:04.564Z","category_id":13120,"game_id":null,"invalid_count":null,"category":{"id":13120,"title":"dirty words","created_at":"2014-02-14T02:04:04.042Z","updated_at":"2014-02-14T02:04:04.042Z","clues_count":5}},{"id":98176,"answer":"Germany","question":"Led by Hans \u0026 Sophie Scholl, the White Rose was a group of student rebels fighting against fascism here in 1943","value":600,"airdate":"2010-02-11T12:00:00.000Z","created_at":"2014-02-14T02:04:04.614Z","updated_at":"2014-02-14T02:04:04.614Z","category_id":13117,"game_id":null,"invalid_count":null,"category":{"id":13117,"title":"power to the students!","created_at":"2014-02-14T02:04:03.991Z","updated_at":"2014-02-14T02:04:03.991Z","clues_count":5}},{"id":98177,"answer":"Jackie Chan","question":"Appropriately, this martial arts master's voice is heard in \"Kung Fu Panda\", as the monkey","value":600,"airdate":"2010-02-11T12:00:00.000Z","created_at":"2014-02-14T02:04:04.651Z","updated_at":"2014-02-14T02:04:04.651Z","category_id":749,"game_id":null,"invalid_count":null,"category":{"id":749,"title":"actors \u0026 actresses","created_at":"2014-02-11T22:50:06.107Z","updated_at":"2014-02-11T22:50:06.107Z","clues_count":60}},{"id":98178,"answer":"character witnesses","question":"In olden law, compurgators were these witnesses who swore to faith in the accused, not to knowing the facts","value":600,"airdate":"2010-02-11T12:00:00.000Z","created_at":"2014-02-14T02:04:04.687Z","updated_at":"2014-02-14T02:04:04.687Z","category_id":13118,"game_id":null,"invalid_count":null,"category":{"id":13118,"title":"can i get a witness?","created_at":"2014-02-14T02:04:04.011Z","updated_at":"2014-02-14T02:04:04.011Z","clues_count":5}},{"id":98179,"answer":"Mexico","question":"Tabasco Hoy","value":600,"airdate":"2010-02-11T12:00:00.000Z","created_at":"2014-02-14T02:04:04.729Z","updated_at":"2014-02-14T02:04:04.729Z","category_id":7098,"game_id":null,"invalid_count":null,"category":{"id":7098,"title":"countries by newspaper","created_at":"2014-02-11T23:20:29.738Z","updated_at":"2014-02-11T23:20:29.738Z","clues_count":10}},{"id":98180,"answer":"the subway","question":"The Kasai station on this Tokyo transport system has a garage for 9,400 bikes","value":600,"airdate":"2010-02-11T12:00:00.000Z","created_at":"2014-02-14T02:04:04.770Z","updated_at":"2014-02-14T02:04:04.770Z","category_id":13119,"game_id":null,"invalid_count":null,"category":{"id":13119,"title":"cycle of life","created_at":"2014-02-14T02:04:04.028Z","updated_at":"2014-02-14T02:04:04.028Z","clues_count":5}},{"id":98181,"answer":"a tarnish","question":"On contact with sulfur, silver develops this discoloration, from the Middle French for \"to dull\"","value":600,"airdate":"2010-02-11T12:00:00.000Z","created_at":"2014-02-14T02:04:04.813Z","updated_at":"2014-02-14T02:04:04.813Z","category_id":13120,"game_id":null,"invalid_count":null,"category":{"id":13120,"title":"dirty words","created_at":"2014-02-14T02:04:04.042Z","updated_at":"2014-02-14T02:04:04.042Z","clues_count":5}},{"id":98182,"answer":"Tiananmen Square","question":"A Beijing University student, Wu'er Kaixi was one of the main leaders during the bloody suppression at this location in 1989","value":800,"airdate":"2010-02-11T12:00:00.000Z","created_at":"2014-02-14T02:04:04.853Z","updated_at":"2014-02-14T02:04:04.853Z","category_id":13117,"game_id":null,"invalid_count":null,"category":{"id":13117,"title":"power to the students!","created_at":"2014-02-14T02:04:03.991Z","updated_at":"2014-02-14T02:04:03.991Z","clues_count":5}},{"id":98183,"answer":"(Megan) Fox","question":"In 2009's \"Jennifer's Body\", she played the title cheerleader with an eating disorder--she's a man-eating demon","value":800,"airdate":"2010-02-11T12:00:00.000Z","created_at":"2014-02-14T02:04:04.896Z","updated_at":"2014-02-14T02:04:04.896Z","category_id":749,"game_id":null,"invalid_count":null,"category":{"id":749,"title":"actors \u0026 actresses","created_at":"2014-02-11T22:50:06.107Z","updated_at":"2014-02-11T22:50:06.107Z","clues_count":60}},{"id":98185,"answer":"Hungary","question":"Magyar Nemzet","value":800,"airdate":"2010-02-11T12:00:00.000Z","created_at":"2014-02-14T02:04:04.971Z","updated_at":"2014-02-14T02:04:04.971Z","category_id":7098,"game_id":null,"invalid_count":null,"category":{"id":7098,"title":"countries by newspaper","created_at":"2014-02-11T23:20:29.738Z","updated_at":"2014-02-11T23:20:29.738Z","clues_count":10}},{"id":98186,"answer":"California","question":"The USA's highest rate of bike use, 2 in 5 calling it their main mode of transport, is in Davis, a college town in this state","value":800,"airdate":"2010-02-11T12:00:00.000Z","created_at":"2014-02-14T02:04:05.010Z","updated_at":"2014-02-14T02:04:05.010Z","category_id":13119,"game_id":null,"invalid_count":null,"category":{"id":13119,"title":"cycle of life","created_at":"2014-02-14T02:04:04.028Z","updated_at":"2014-02-14T02:04:04.028Z","clues_count":5}},{"id":98187,"answer":"unclean","question":"Leviticus 11 warns against eating swine: \"Though he divide the hoof...yet he cheweth not the cud; he is\" this","value":800,"airdate":"2010-02-11T12:00:00.000Z","created_at":"2014-02-14T02:04:05.047Z","updated_at":"2014-02-14T02:04:05.047Z","category_id":13120,"game_id":null,"invalid_count":null,"category":{"id":13120,"title":"dirty words","created_at":"2014-02-14T02:04:04.042Z","updated_at":"2014-02-14T02:04:04.042Z","clues_count":5}},{"id":98188,"answer":"the Velvet Revolution","question":"This fabric-named 1989 revolution in Czechoslovakia began after police attacked a student demonstration","value":1000,"airdate":"2010-02-11T12:00:00.000Z","created_at":"2014-02-14T02:04:05.083Z","updated_at":"2014-02-14T02:04:05.083Z","category_id":13117,"game_id":null,"invalid_count":null,"category":{"id":13117,"title":"power to the students!","created_at":"2014-02-14T02:04:03.991Z","updated_at":"2014-02-14T02:04:03.991Z","clues_count":5}},{"id":98189,"answer":"Ellen Page","question":"She did most of her own rollerskating as Bliss (aka Babe Ruthless) in \"Whip It\"","value":1000,"airdate":"2010-02-11T12:00:00.000Z","created_at":"2014-02-14T02:04:05.129Z","updated_at":"2014-02-14T02:04:05.129Z","category_id":749,"game_id":null,"invalid_count":null,"category":{"id":749,"title":"actors \u0026 actresses","created_at":"2014-02-11T22:50:06.107Z","updated_at":"2014-02-11T22:50:06.107Z","clues_count":60}},{"id":98190,"answer":"the U.S. Marshals Service","question":"It's in plain sight that the U.S. law enforcement service is responsible for witness security","value":1000,"airdate":"2010-02-11T12:00:00.000Z","created_at":"2014-02-14T02:04:05.169Z","updated_at":"2014-02-14T02:04:05.169Z","category_id":13118,"game_id":null,"invalid_count":null,"category":{"id":13118,"title":"can i get a witness?","created_at":"2014-02-14T02:04:04.011Z","updated_at":"2014-02-14T02:04:04.011Z","clues_count":5}},{"id":98191,"answer":"Vietnam","question":"Nhan Dan","value":1000,"airdate":"2010-02-11T12:00:00.000Z","created_at":"2014-02-14T02:04:05.208Z","updated_at":"2014-02-14T02:04:05.208Z","category_id":7098,"game_id":null,"invalid_count":null,"category":{"id":7098,"title":"countries by newspaper","created_at":"2014-02-11T23:20:29.738Z","updated_at":"2014-02-11T23:20:29.738Z","clues_count":10}},{"id":98192,"answer":"quadriceps","question":"In addition to a cardio workout, cycling gives strength to muscles like this 4-part one at the front of the thigh","value":null,"airdate":"2010-02-11T12:00:00.000Z","created_at":"2014-02-14T02:04:05.247Z","updated_at":"2014-02-14T02:04:05.247Z","category_id":13119,"game_id":null,"invalid_count":null,"category":{"id":13119,"title":"cycle of life","created_at":"2014-02-14T02:04:04.028Z","updated_at":"2014-02-14T02:04:04.028Z","clues_count":5}},{"id":98193,"answer":"smut","question":"It can be a dirt particle, a parasitic fungal disease...or pornography","value":1000,"airdate":"2010-02-11T12:00:00.000Z","created_at":"2014-02-14T02:04:05.287Z","updated_at":"2014-02-14T02:04:05.287Z","category_id":13120,"game_id":null,"invalid_count":null,"category":{"id":13120,"title":"dirty words","created_at":"2014-02-14T02:04:04.042Z","updated_at":"2014-02-14T02:04:04.042Z","clues_count":5}},{"id":98184,"answer":"affirm","question":"(Jimmy of the Clue Crew reports from a courtroom.)  A witness doesn't have to swear to tell the truth; some, for reasons of religion or lack of religion, prefer this word, also an option in the presidential oath of office","value":800,"airdate":"2010-02-11T12:00:00.000Z","created_at":"2014-02-14T02:04:04.934Z","updated_at":"2016-04-05T17:30:07.218Z","category_id":13118,"game_id":null,"invalid_count":1,"category":{"id":13118,"title":"can i get a witness?","created_at":"2014-02-14T02:04:04.011Z","updated_at":"2014-02-14T02:04:04.011Z","clues_count":5}}]